Guia 09/verilog/clock.v
// Arthur Signorini Miranda
// 848122

// clock.v - Gerador de clock

module clock (output reg clk);
    initial begin
        clk = 1'b0;
    end

    always begin
        #12 clk = ~clk;  // Clock alterna a cada 12 unidades de tempo
    end
endmodule

Guia 09/verilog/Guia_0906.v
// Arthur Signorini Miranda
// 848122

// Guia_0906.v - Pulso com marcação de 5 unidades de tempo na borda de descida do clock
`include "clock.v"

module pulse_5_time (output reg signal, input clock);
    always @ (negedge clock) begin
        signal = 1'b1;
        #5 signal = 1'b0;
    end
endmodule

module Guia_0906;
    wire clock;
    clock clk (clock);

    wire p1;
    pulse_5_time pls1 (p1, clock);

    initial begin
        $dumpfile("Guia_0906.vcd");  // Geração do arquivo .vcd
        $dumpvars(1, clock, p1);

        #480 $finish;  // Finaliza a simulação após 480 unidades de tempo
    end
endmodule

Guia 09/.vcd/Guia_0906.vcd
$date
	Sun Sep 29 18:13:27 2024
$end
$version
	Icarus Verilog
$end
$timescale
	1s
$end
$scope module Guia_0906 $end
$var wire 1 ! clock $end
$upscope $end
$scope module Guia_0906 $end
$var wire 1 " p1 $end
$upscope $end
$enddefinitions $end
$comment Show the parameter values. $end
$dumpall
$end
#0
$dumpvars
x"
0!
$end
#12
1!
#24
1"
0!
#29
0"
#36
1!
#48
1"
0!
#53
0"
#60
1!
#72
1"
0!
#77
0"
#84
1!
#96
1"
0!
#101
0"
#108
1!
#120
1"
0!
#125
0"
#132
1!
#144
1"
0!
#149
0"
#156
1!
#168
1"
0!
#173
0"
#180
1!
#192
1"
0!
#197
0"
#204
1!
#216
1"
0!
#221
0"
#228
1!
#240
1"
0!
#245
0"
#252
1!
#264
1"
0!
#269
0"
#276
1!
#288
1"
0!
#293
0"
#300
1!
#312
1"
0!
#317
0"
#324
1!
#336
1"
0!
#341
0"
#348
1!
#360
1"
0!
#365
0"
#372
1!
#384
1"
0!
#389
0"
#396
1!
#408
1"
0!
#413
0"
#420
1!
#432
1"
0!
#437
0"
#444
1!
#456
1"
0!
#461
0"
#468
1!
#480
1"
0!
