Guia 09/verilog/clock.v
// Arthur Signorini Miranda
// 848122

// clock.v - Gerador de clock

module clock (output reg clk);
    initial begin
        clk = 1'b0;
    end

    always begin
        #12 clk = ~clk;  // Clock alterna a cada 12 unidades de tempo
    end
endmodule

Guias/Guia 09/verilog/Guia_0907.v
// Arthur Signorini Miranda
// 848122

// Guia_0907.v - Pulso com marcação de 8 unidades de tempo no nível alto do clock
`include "clock.v"

module pulse_8_time (output reg signal, input clock);
    always @ (clock) begin
        if (clock == 1'b1) begin
            signal = 1'b1;
            #8 signal = 1'b0;
        end
    end
endmodule

module Guia_0907;
    wire clock;
    clock clk (clock);

    wire p1;
    pulse_8_time pls1 (p1, clock);

    initial begin
        $dumpfile("Guia_0907.vcd");  // Geração do arquivo .vcd
        $dumpvars(1, clock, p1);

        #480 $finish;  // Finaliza a simulação após 480 unidades de tempo
    end
endmodule

Guia 09/.vcd/Guia_0907.vcd
$date
	Sun Sep 29 18:14:06 2024
$end
$version
	Icarus Verilog
$end
$timescale
	1s
$end
$scope module Guia_0907 $end
$var wire 1 ! clock $end
$upscope $end
$scope module Guia_0907 $end
$var wire 1 " p1 $end
$upscope $end
$enddefinitions $end
$comment Show the parameter values. $end
$dumpall
$end
#0
$dumpvars
x"
0!
$end
#12
1"
1!
#20
0"
#24
0!
#36
1"
1!
#44
0"
#48
0!
#60
1"
1!
#68
0"
#72
0!
#84
1"
1!
#92
0"
#96
0!
#108
1"
1!
#116
0"
#120
0!
#132
1"
1!
#140
0"
#144
0!
#156
1"
1!
#164
0"
#168
0!
#180
1"
1!
#188
0"
#192
0!
#204
1"
1!
#212
0"
#216
0!
#228
1"
1!
#236
0"
#240
0!
#252
1"
1!
#260
0"
#264
0!
#276
1"
1!
#284
0"
#288
0!
#300
1"
1!
#308
0"
#312
0!
#324
1"
1!
#332
0"
#336
0!
#348
1"
1!
#356
0"
#360
0!
#372
1"
1!
#380
0"
#384
0!
#396
1"
1!
#404
0"
#408
0!
#420
1"
1!
#428
0"
#432
0!
#444
1"
1!
#452
0"
#456
0!
#468
1"
1!
#476
0"
